solutionmaker/__init__.py
solutionmaker/cli.py
solutionmaker/templates/main.py
solutionmaker/templates/bin/__init__.py
solutionmaker/templates/bin/logic/__init__.py
solutionmaker/templates/bin/logic/filesystem.py
solutionmaker/templates/bin/logic/geo.py
solutionmaker/templates/bin/logic/parser.py
solutionmaker/templates/bin/logic/web.py
solutionmaker/templates/bin/settings/__init__.py
solutionmaker/templates/bin/settings/settings.py
solutionmaker/templates/results/.gitkeep
solutionmaker/templates/source/.gitkeep
solutionmaker-0.1.0.dist-info/METADATA
solutionmaker-0.1.0.dist-info/WHEEL
solutionmaker-0.1.0.dist-info/entry_points.txt
solutionmaker-0.1.0.dist-info/top_level.txt
solutionmaker-0.1.0.dist-info/RECORD
